pysoem/__init__.py
pysoem/pysoem.cpython-314-darwin.so
pysoem-1.1.13.dist-info/RECORD
pysoem-1.1.13.dist-info/WHEEL
pysoem-1.1.13.dist-info/top_level.txt
pysoem-1.1.13.dist-info/METADATA
pysoem-1.1.13.dist-info/licenses/LICENSE
